relpy/__init__.py
relpy-0.0.1.dist-info/LICENSE
relpy-0.0.1.dist-info/METADATA
relpy-0.0.1.dist-info/WHEEL
relpy-0.0.1.dist-info/top_level.txt
relpy-0.0.1.dist-info/RECORD
